jania/__init__.py
jania/cleanJSON.py
jania/configenv.py
jania/extractPDF.py
jania-0.3.13.dist-info/METADATA
jania-0.3.13.dist-info/WHEEL
jania-0.3.13.dist-info/top_level.txt
jania-0.3.13.dist-info/RECORD
