Metadata-Version: 2.4
Name: jania
Version: 0.3.13
Summary: Multipurpose python utils
Author-email: Julian Ania <julian.ania@zebraventures.eu>
Project-URL: Homepage, https://github.com/julianin/JANIALIB
Keywords: utils,jania
Classifier: Programming Language :: Python :: 3
Classifier: Operating System :: OS Independent
Classifier: License :: OSI Approved :: MIT License
Requires-Dist: toml
Requires-Dist: PyYAML
Requires-Dist: python-dotenv
Requires-Dist: pymupdf
Requires-Dist: Pillow
Requires-Dist: openai
